nosorog/__init__.py
nosorog/__version__.py
nosorog-0.2.0.dist-info/LICENSE
nosorog-0.2.0.dist-info/METADATA
nosorog-0.2.0.dist-info/WHEEL
nosorog-0.2.0.dist-info/top_level.txt
nosorog-0.2.0.dist-info/RECORD
