Metadata-Version: 2.1
Name: nosorog
Version: 0.2.0
Summary: An assertive security library.
Home-page: https://nosorog.readthedocs.io
Author: Vyacheslav Lobanov
Author-email: bartoldo@bk.ru
License: Apache 2.0
Project-URL: Documentation, https://nosorog.readthedocs.io
Project-URL: Source, https://github.com/vyacheslavlobanov/nosorog
Keywords: security,protect,nosorog
Platform: UNKNOWN
Classifier: Development Status :: 3 - Alpha
Classifier: Intended Audience :: Developers
Classifier: License :: OSI Approved :: Apache Software License
Classifier: Natural Language :: English
Classifier: Operating System :: OS Independent
Classifier: Programming Language :: Python
Classifier: Programming Language :: Python :: 3.7
Classifier: Programming Language :: Python :: 3 :: Only
Classifier: Programming Language :: Python :: Implementation :: CPython
Classifier: Programming Language :: Python :: Implementation :: PyPy
Classifier: Topic :: Security
Classifier: Topic :: Software Development :: Libraries
Requires-Python: >=3.7, <4
License-File: LICENSE
